[
    {
        "NumTour":"1",
        "CodDpt":"44",
        "LibDpt":"Loire-Atlantique",
        "CodCirElec":"4402",
        "LibCirElec":"2ème circonscription",
        "PrenomPsn":"Andy",
        "NomPsn":"KERBRAT",
        "LibNuaCand":"Nouveau Front populaire (LFI)",
        "Couleur":"#db1616",
        "Sortant":"sortant",
        "Details":null
    },
    {
        "NumTour":"1",
        "CodDpt":"44",
        "LibDpt":"Loire-Atlantique",
        "CodCirElec":"4402",
        "LibCirElec":"2ème circonscription",
        "PrenomPsn":"Louisa",
        "NomPsn":"AMROUCHE",
        "LibNuaCand":"Les Républicains",
        "Couleur":"#005ce6",
        "Sortant":null,
        "Details":null
    },
    {
        "NumTour":"1",
        "CodDpt":"44",
        "LibDpt":"Loire-Atlantique",
        "CodCirElec":"4402",
        "LibCirElec":"2ème circonscription",
        "PrenomPsn":"Nicolas",
        "NomPsn":"BAZILLE",
        "LibNuaCand":"Lutte ouvrière",
        "Couleur":"#AF0000",
        "Sortant":null,
        "Details":null
    },
    {
        "NumTour":"1",
        "CodDpt":"44",
        "LibDpt":"Loire-Atlantique",
        "CodCirElec":"4402",
        "LibCirElec":"2ème circonscription",
        "PrenomPsn":"Zora",
        "NomPsn":"CHIGNOLE",
        "LibNuaCand":null,
        "Couleur":null,
        "Sortant":null,
        "Details":null
    },
    {
        "NumTour":"1",
        "CodDpt":"44",
        "LibDpt":"Loire-Atlantique",
        "CodCirElec":"4402",
        "LibCirElec":"2ème circonscription",
        "PrenomPsn":"Adrien",
        "NomPsn":"COPROS",
        "LibNuaCand":"Volt France",
        "Couleur":null,
        "Sortant":null,
        "Details":null
    },
    {
        "NumTour":"1",
        "CodDpt":"44",
        "LibDpt":"Loire-Atlantique",
        "CodCirElec":"4402",
        "LibCirElec":"2ème circonscription",
        "PrenomPsn":"Nolwenn",
        "NomPsn":"FER",
        "LibNuaCand":"Rassemblement national",
        "Couleur":"#002E61",
        "Sortant":null,
        "Details":null
    },
    {
        "NumTour":"1",
        "CodDpt":"44",
        "LibDpt":"Loire-Atlantique",
        "CodCirElec":"4402",
        "LibCirElec":"2ème circonscription",
        "PrenomPsn":"Valérie",
        "NomPsn":"OPPELT",
        "LibNuaCand":"Renaissance",
        "Couleur":"#9859fc",
        "Sortant":null,
        "Details":null
    },
    {
        "NumTour":"1",
        "CodDpt":"44",
        "LibDpt":"Loire-Atlantique",
        "CodCirElec":"4402",
        "LibCirElec":"2ème circonscription",
        "PrenomPsn":"Nicolas",
        "NomPsn":"VABRE",
        "LibNuaCand":"Nouveau parti anticapitaliste (NPA)",
        "Couleur":"#af0000",
        "Sortant":null,
        "Details":null
    }
]