[
    {
        "NumTour":"1",
        "CodDpt":"03",
        "LibDpt":"Allier",
        "CodCirElec":"0301",
        "LibCirElec":"1ère circonscription",
        "NumPanneauCand":"1",
        "PrenomPsn":"Blandine",
        "NomPsn":"AGEZ",
        "CodNuaCand":"REC",
        "LibNuaCand":"Reconquête !",
        "Couleur":"#1019c1",
        "Sortant":null,
        "Details":null
    },
    {
        "NumTour":"1",
        "CodDpt":"03",
        "LibDpt":"Allier",
        "CodCirElec":"0301",
        "LibCirElec":"1ère circonscription",
        "NumPanneauCand":"2",
        "PrenomPsn":"Yannick",
        "NomPsn":"MONNET",
        "CodNuaCand":"UG",
        "LibNuaCand":"Union de la gauche",
        "Couleur":null,
        "Sortant":null,
        "Details":null
    },
    {
        "NumTour":"1",
        "CodDpt":"03",
        "LibDpt":"Allier",
        "CodCirElec":"0301",
        "LibCirElec":"1ère circonscription",
        "NumPanneauCand":"3",
        "PrenomPsn":"Jean-Marie",
        "NomPsn":"GUILLAUMIN",
        "CodNuaCand":"UDI",
        "LibNuaCand":"Union des Démocrates et Indépendants",
        "Couleur":null,
        "Sortant":null,
        "Details":null
    },
    {
        "NumTour":"1",
        "CodDpt":"03",
        "LibDpt":"Allier",
        "CodCirElec":"0301",
        "LibCirElec":"1ère circonscription",
        "NumPanneauCand":"4",
        "PrenomPsn":"Jean-Marc",
        "NomPsn":"COLLOT",
        "CodNuaCand":"EXG",
        "LibNuaCand":"Extrême gauche",
        "Couleur":null,
        "Sortant":null,
        "Details":null
    },
    {
        "NumTour":"1",
        "CodDpt":"03",
        "LibDpt":"Allier",
        "CodCirElec":"0301",
        "LibCirElec":"1ère circonscription",
        "NumPanneauCand":"5",
        "PrenomPsn":"Stephane",
        "NomPsn":"LARZAT",
        "CodNuaCand":"ENS",
        "LibNuaCand":"Ensemble ! (Majorité présidentielle)",
        "Couleur":null,
        "Sortant":null,
        "Details":null
    },
    {
        "NumTour":"1",
        "CodDpt":"03",
        "LibDpt":"Allier",
        "CodCirElec":"0301",
        "LibCirElec":"1ère circonscription",
        "NumPanneauCand":"6",
        "PrenomPsn":"Alexandra",
        "NomPsn":"BARDET",
        "CodNuaCand":"LR",
        "LibNuaCand":"Les Républicains",
        "Couleur":"#005ce6",
        "Sortant":null,
        "Details":null
    },
    {
        "NumTour":"1",
        "CodDpt":"03",
        "LibDpt":"Allier",
        "CodCirElec":"0301",
        "LibCirElec":"1ère circonscription",
        "NumPanneauCand":"7",
        "PrenomPsn":"Anne-Marie",
        "NomPsn":"THÈS",
        "CodNuaCand":"RN",
        "LibNuaCand":"Rassemblement National",
        "Couleur":null,
        "Sortant":null,
        "Details":null
    }
]