[
    {
        "NumTour":"1",
        "CodDpt":"30",
        "LibDpt":"Gard",
        "CodCirElec":"3005",
        "LibCirElec":"5ème circonscription",
        "NumPanneauCand":"1",
        "PrenomPsn":"Emmanuel",
        "NomPsn":"ESPANOL",
        "CodNuaCand":"EXD",
        "LibNuaCand":"Extrême droite",
        "Couleur":"#1019c1",
        "Sortant":null,
        "Details":null
    },
    {
        "NumTour":"1",
        "CodDpt":"30",
        "LibDpt":"Gard",
        "CodCirElec":"3005",
        "LibCirElec":"5ème circonscription",
        "NumPanneauCand":"2",
        "PrenomPsn":"Léa",
        "NomPsn":"BOYER",
        "CodNuaCand":"LR",
        "LibNuaCand":"Les Républicains",
        "Couleur":"#005ce6",
        "Sortant":null,
        "Details":null
    },
    {
        "NumTour":"1",
        "CodDpt":"30",
        "LibDpt":"Gard",
        "CodCirElec":"3005",
        "LibCirElec":"5ème circonscription",
        "NumPanneauCand":"3",
        "PrenomPsn":"Alexandre",
        "NomPsn":"ALLEGRET-PILOT",
        "CodNuaCand":"UXD",
        "LibNuaCand":"Union de l'extrême droite",
        "Couleur":"#1019c1",
        "Sortant":null,
        "Details":null
    },
    {
        "NumTour":"1",
        "CodDpt":"30",
        "LibDpt":"Gard",
        "CodCirElec":"3005",
        "LibCirElec":"5ème circonscription",
        "NumPanneauCand":"4",
        "PrenomPsn":"Michel",
        "NomPsn":"SALA",
        "CodNuaCand":"UG",
        "LibNuaCand":"Union de la gauche",
        "Couleur":"#de3c80",
        "Sortant":null,
        "Details":null
    },
    {
        "NumTour":"1",
        "CodDpt":"30",
        "LibDpt":"Gard",
        "CodCirElec":"3005",
        "LibCirElec":"5ème circonscription",
        "NumPanneauCand":"5",
        "PrenomPsn":"Agnès",
        "NomPsn":"OLINET",
        "CodNuaCand":"EXG",
        "LibNuaCand":"Extrême gauche",
        "Couleur":"#AF0000",
        "Sortant":null,
        "Details":null
    },
    {
        "NumTour":"1",
        "CodDpt":"30",
        "LibDpt":"Gard",
        "CodCirElec":"3005",
        "LibCirElec":"5ème circonscription",
        "NumPanneauCand":"6",
        "PrenomPsn":"Nordine",
        "NomPsn":"TRIA",
        "CodNuaCand":"DIV",
        "LibNuaCand":"Divers",
        "Couleur":null,
        "Sortant":null,
        "Details":null
    },
    {
        "NumTour":"1",
        "CodDpt":"30",
        "LibDpt":"Gard",
        "CodCirElec":"3005",
        "LibCirElec":"5ème circonscription",
        "NumPanneauCand":"7",
        "PrenomPsn":"Catherine",
        "NomPsn":"DAUFÈS-ROUX",
        "CodNuaCand":"ENS",
        "LibNuaCand":"Ensemble ! (Majorité présidentielle)",
        "Couleur":"#9859fc",
        "Sortant":null,
        "Details":null
    }
]