[
    {
        "NumTour":"1",
        "CodDpt":"54",
        "LibDpt":"Meurthe-et-Moselle",
        "CodCirElec":"5401",
        "LibCirElec":"1ère circonscription",
        "NumPanneauCand":"1",
        "PrenomPsn":"Estelle",
        "NomPsn":"MERCIER",
        "CodNuaCand":"UG",
        "LibNuaCand":"Union de la gauche",
        "Couleur":"#de3c80",
        "Sortant":null,
        "Details":null
    },
    {
        "NumTour":"1",
        "CodDpt":"54",
        "LibDpt":"Meurthe-et-Moselle",
        "CodCirElec":"5401",
        "LibCirElec":"1ère circonscription",
        "NumPanneauCand":"2",
        "PrenomPsn":"Christiane",
        "NomPsn":"NIMSGERN",
        "CodNuaCand":"EXG",
        "LibNuaCand":"Extrême gauche",
        "Couleur":"#AF0000",
        "Sortant":null,
        "Details":null
    },
    {
        "NumTour":"1",
        "CodDpt":"54",
        "LibDpt":"Meurthe-et-Moselle",
        "CodCirElec":"5401",
        "LibCirElec":"1ère circonscription",
        "NumPanneauCand":"3",
        "PrenomPsn":"Aurélien",
        "NomPsn":"ARNOULD",
        "CodNuaCand":"LR",
        "LibNuaCand":"Les Républicains",
        "Couleur":"#005ce6",
        "Sortant":null,
        "Details":null
    },
    {
        "NumTour":"1",
        "CodDpt":"54",
        "LibDpt":"Meurthe-et-Moselle",
        "CodCirElec":"5401",
        "LibCirElec":"1ère circonscription",
        "NumPanneauCand":"4",
        "PrenomPsn":"Patricia",
        "NomPsn":"MELET",
        "CodNuaCand":"RN",
        "LibNuaCand":"Rassemblement National",
        "Couleur":"#002E61",
        "Sortant":null,
        "Details":null
    },
    {
        "NumTour":"1",
        "CodDpt":"54",
        "LibDpt":"Meurthe-et-Moselle",
        "CodCirElec":"5401",
        "LibCirElec":"1ère circonscription",
        "NumPanneauCand":"5",
        "PrenomPsn":"Philippe",
        "NomPsn":"GUILLEMARD",
        "CodNuaCand":"ENS",
        "LibNuaCand":"Ensemble ! (Majorité présidentielle)",
        "Couleur":"#9859fc",
        "Sortant":null,
        "Details":null
    },
    {
        "NumTour":"1",
        "CodDpt":"54",
        "LibDpt":"Meurthe-et-Moselle",
        "CodCirElec":"5401",
        "LibCirElec":"1ère circonscription",
        "NumPanneauCand":"6",
        "PrenomPsn":"Massimo",
        "NomPsn":"NESPOLO",
        "CodNuaCand":"DSV",
        "LibNuaCand":"Droite souverainiste",
        "Couleur":"#1019c1",
        "Sortant":null,
        "Details":null
    },
    {
        "NumTour":"1",
        "CodDpt":"54",
        "LibDpt":"Meurthe-et-Moselle",
        "CodCirElec":"5402",
        "LibCirElec":"2ème circonscription",
        "NumPanneauCand":"1",
        "PrenomPsn":"Geneviève",
        "NomPsn":"MAILLOT",
        "CodNuaCand":"RN",
        "LibNuaCand":"Rassemblement National",
        "Couleur":"#002E61",
        "Sortant":null,
        "Details":null
    },
    {
        "NumTour":"1",
        "CodDpt":"54",
        "LibDpt":"Meurthe-et-Moselle",
        "CodCirElec":"5402",
        "LibCirElec":"2ème circonscription",
        "NumPanneauCand":"2",
        "PrenomPsn":"Sloane",
        "NomPsn":"FROMONT",
        "CodNuaCand":"LR",
        "LibNuaCand":"Les Républicains",
        "Couleur":"#005ce6",
        "Sortant":null,
        "Details":null
    },
    {
        "NumTour":"1",
        "CodDpt":"54",
        "LibDpt":"Meurthe-et-Moselle",
        "CodCirElec":"5402",
        "LibCirElec":"2ème circonscription",
        "NumPanneauCand":"3",
        "PrenomPsn":"Emmanuel",
        "NomPsn":"LACRESSE",
        "CodNuaCand":"ENS",
        "LibNuaCand":"Ensemble ! (Majorité présidentielle)",
        "Couleur":"#9859fc",
        "Sortant":null,
        "Details":null
    },
    {
        "NumTour":"1",
        "CodDpt":"54",
        "LibDpt":"Meurthe-et-Moselle",
        "CodCirElec":"5402",
        "LibCirElec":"2ème circonscription",
        "NumPanneauCand":"4",
        "PrenomPsn":"Odile",
        "NomPsn":"DESTOMBES",
        "CodNuaCand":"EXG",
        "LibNuaCand":"Extrême gauche",
        "Couleur":"#AF0000",
        "Sortant":null,
        "Details":null
    },
    {
        "NumTour":"1",
        "CodDpt":"54",
        "LibDpt":"Meurthe-et-Moselle",
        "CodCirElec":"5402",
        "LibCirElec":"2ème circonscription",
        "NumPanneauCand":"5",
        "PrenomPsn":"Stéphane",
        "NomPsn":"HABLOT",
        "CodNuaCand":"UG",
        "LibNuaCand":"Union de la gauche",
        "Couleur":"#de3c80",
        "Sortant":null,
        "Details":null
    },
    {
        "NumTour":"1",
        "CodDpt":"54",
        "LibDpt":"Meurthe-et-Moselle",
        "CodCirElec":"5402",
        "LibCirElec":"2ème circonscription",
        "NumPanneauCand":"6",
        "PrenomPsn":"Lucy",
        "NomPsn":"GEORGES",
        "CodNuaCand":"REC",
        "LibNuaCand":"Reconquête !",
        "Couleur":"#1019c1",
        "Sortant":null,
        "Details":null
    },
    {
        "NumTour":"1",
        "CodDpt":"54",
        "LibDpt":"Meurthe-et-Moselle",
        "CodCirElec":"5403",
        "LibCirElec":"3ème circonscription",
        "NumPanneauCand":"1",
        "PrenomPsn":"Xavier",
        "NomPsn":"BOURY",
        "CodNuaCand":"EXG",
        "LibNuaCand":"Extrême gauche",
        "Couleur":"#AF0000",
        "Sortant":null,
        "Details":null
    },
    {
        "NumTour":"1",
        "CodDpt":"54",
        "LibDpt":"Meurthe-et-Moselle",
        "CodCirElec":"5403",
        "LibCirElec":"3ème circonscription",
        "NumPanneauCand":"2",
        "PrenomPsn":"Frédéric",
        "NomPsn":"WEBER",
        "CodNuaCand":"RN",
        "LibNuaCand":"Rassemblement National",
        "Couleur":"#002E61",
        "Sortant":null,
        "Details":null
    },
    {
        "NumTour":"1",
        "CodDpt":"54",
        "LibDpt":"Meurthe-et-Moselle",
        "CodCirElec":"5403",
        "LibCirElec":"3ème circonscription",
        "NumPanneauCand":"3",
        "PrenomPsn":"Mathieu",
        "NomPsn":"SERVAGI",
        "CodNuaCand":"LR",
        "LibNuaCand":"Les Républicains",
        "Couleur":"#005ce6",
        "Sortant":null,
        "Details":null
    },
    {
        "NumTour":"1",
        "CodDpt":"54",
        "LibDpt":"Meurthe-et-Moselle",
        "CodCirElec":"5403",
        "LibCirElec":"3ème circonscription",
        "NumPanneauCand":"4",
        "PrenomPsn":"Martine",
        "NomPsn":"ETIENNE",
        "CodNuaCand":"UG",
        "LibNuaCand":"Union de la gauche",
        "Couleur":"#de3c80",
        "Sortant":null,
        "Details":null
    },
    {
        "NumTour":"1",
        "CodDpt":"54",
        "LibDpt":"Meurthe-et-Moselle",
        "CodCirElec":"5403",
        "LibCirElec":"3ème circonscription",
        "NumPanneauCand":"5",
        "PrenomPsn":"Valérie",
        "NomPsn":"MAURICE",
        "CodNuaCand":"ENS",
        "LibNuaCand":"Ensemble ! (Majorité présidentielle)",
        "Couleur":"#9859fc",
        "Sortant":null,
        "Details":null
    },
    {
        "NumTour":"1",
        "CodDpt":"54",
        "LibDpt":"Meurthe-et-Moselle",
        "CodCirElec":"5404",
        "LibCirElec":"4ème circonscription",
        "NumPanneauCand":"1",
        "PrenomPsn":"Geneviève",
        "NomPsn":"HEILLIETTE",
        "CodNuaCand":"EXG",
        "LibNuaCand":"Extrême gauche",
        "Couleur":"#AF0000",
        "Sortant":null,
        "Details":null
    },
    {
        "NumTour":"1",
        "CodDpt":"54",
        "LibDpt":"Meurthe-et-Moselle",
        "CodCirElec":"5404",
        "LibCirElec":"4ème circonscription",
        "NumPanneauCand":"2",
        "PrenomPsn":"Valérie",
        "NomPsn":"CANTIGET",
        "CodNuaCand":"REC",
        "LibNuaCand":"Reconquête !",
        "Couleur":"#1019c1",
        "Sortant":null,
        "Details":null
    },
    {
        "NumTour":"1",
        "CodDpt":"54",
        "LibDpt":"Meurthe-et-Moselle",
        "CodCirElec":"5404",
        "LibCirElec":"4ème circonscription",
        "NumPanneauCand":"3",
        "PrenomPsn":"Barbara",
        "NomPsn":"BERTOZZI-BIÉVELOT",
        "CodNuaCand":"UG",
        "LibNuaCand":"Union de la gauche",
        "Couleur":"#de3c80",
        "Sortant":null,
        "Details":null
    },
    {
        "NumTour":"1",
        "CodDpt":"54",
        "LibDpt":"Meurthe-et-Moselle",
        "CodCirElec":"5404",
        "LibCirElec":"4ème circonscription",
        "NumPanneauCand":"4",
        "PrenomPsn":"Dominique",
        "NomPsn":"BILDE",
        "CodNuaCand":"RN",
        "LibNuaCand":"Rassemblement National",
        "Couleur":"#002E61",
        "Sortant":null,
        "Details":null
    },
    {
        "NumTour":"1",
        "CodDpt":"54",
        "LibDpt":"Meurthe-et-Moselle",
        "CodCirElec":"5404",
        "LibCirElec":"4ème circonscription",
        "NumPanneauCand":"5",
        "PrenomPsn":"Thibault",
        "NomPsn":"BAZIN",
        "CodNuaCand":"LR",
        "LibNuaCand":"Les Républicains",
        "Couleur":"#005ce6",
        "Sortant":null,
        "Details":null
    },
    {
        "NumTour":"1",
        "CodDpt":"54",
        "LibDpt":"Meurthe-et-Moselle",
        "CodCirElec":"5405",
        "LibCirElec":"5ème circonscription",
        "NumPanneauCand":"1",
        "PrenomPsn":"Louis-Joseph",
        "NomPsn":"PECHER",
        "CodNuaCand":"UXD",
        "LibNuaCand":"Union de l'extrême droite",
        "Couleur":"#1019c1",
        "Sortant":null,
        "Details":null
    },
    {
        "NumTour":"1",
        "CodDpt":"54",
        "LibDpt":"Meurthe-et-Moselle",
        "CodCirElec":"5405",
        "LibCirElec":"5ème circonscription",
        "NumPanneauCand":"2",
        "PrenomPsn":"Dominique",
        "NomPsn":"POTIER",
        "CodNuaCand":"UG",
        "LibNuaCand":"Union de la gauche",
        "Couleur":"#de3c80",
        "Sortant":null,
        "Details":null
    },
    {
        "NumTour":"1",
        "CodDpt":"54",
        "LibDpt":"Meurthe-et-Moselle",
        "CodCirElec":"5405",
        "LibCirElec":"5ème circonscription",
        "NumPanneauCand":"3",
        "PrenomPsn":"Miriam",
        "NomPsn":"AUBERT",
        "CodNuaCand":"EXG",
        "LibNuaCand":"Extrême gauche",
        "Couleur":"#AF0000",
        "Sortant":null,
        "Details":null
    },
    {
        "NumTour":"1",
        "CodDpt":"54",
        "LibDpt":"Meurthe-et-Moselle",
        "CodCirElec":"5405",
        "LibCirElec":"5ème circonscription",
        "NumPanneauCand":"4",
        "PrenomPsn":"Pierre-Nicolas",
        "NomPsn":"NUPS",
        "CodNuaCand":"EXD",
        "LibNuaCand":"Extrême droite",
        "Couleur":"#1019c1",
        "Sortant":null,
        "Details":null
    },
    {
        "NumTour":"1",
        "CodDpt":"54",
        "LibDpt":"Meurthe-et-Moselle",
        "CodCirElec":"5405",
        "LibCirElec":"5ème circonscription",
        "NumPanneauCand":"5",
        "PrenomPsn":"Edouard",
        "NomPsn":"MATHIEU",
        "CodNuaCand":"DIV",
        "LibNuaCand":"Divers",
        "Couleur":null,
        "Sortant":null,
        "Details":null
    },
    {
        "NumTour":"1",
        "CodDpt":"54",
        "LibDpt":"Meurthe-et-Moselle",
        "CodCirElec":"5405",
        "LibCirElec":"5ème circonscription",
        "NumPanneauCand":"6",
        "PrenomPsn":"Quentin",
        "NomPsn":"VINOT",
        "CodNuaCand":"LR",
        "LibNuaCand":"Les Républicains",
        "Couleur":"#005ce6",
        "Sortant":null,
        "Details":null
    },
    {
        "NumTour":"1",
        "CodDpt":"54",
        "LibDpt":"Meurthe-et-Moselle",
        "CodCirElec":"5406",
        "LibCirElec":"6ème circonscription",
        "NumPanneauCand":"1",
        "PrenomPsn":"Dominique",
        "NomPsn":"BARBIN",
        "CodNuaCand":"EXG",
        "LibNuaCand":"Extrême gauche",
        "Couleur":"#AF0000",
        "Sortant":null,
        "Details":null
    },
    {
        "NumTour":"1",
        "CodDpt":"54",
        "LibDpt":"Meurthe-et-Moselle",
        "CodCirElec":"5406",
        "LibCirElec":"6ème circonscription",
        "NumPanneauCand":"2",
        "PrenomPsn":"Richard",
        "NomPsn":"NOWAK",
        "CodNuaCand":"ECO",
        "LibNuaCand":"Ecologistes",
        "Couleur":"#2ECC2E",
        "Sortant":null,
        "Details":null
    },
    {
        "NumTour":"1",
        "CodDpt":"54",
        "LibDpt":"Meurthe-et-Moselle",
        "CodCirElec":"5406",
        "LibCirElec":"6ème circonscription",
        "NumPanneauCand":"3",
        "PrenomPsn":"Ergün",
        "NomPsn":"TOPARSLAN",
        "CodNuaCand":"ENS",
        "LibNuaCand":"Ensemble ! (Majorité présidentielle)",
        "Couleur":"#9859fc",
        "Sortant":null,
        "Details":null
    },
    {
        "NumTour":"1",
        "CodDpt":"54",
        "LibDpt":"Meurthe-et-Moselle",
        "CodCirElec":"5406",
        "LibCirElec":"6ème circonscription",
        "NumPanneauCand":"4",
        "PrenomPsn":"Jordan",
        "NomPsn":"SIMON",
        "CodNuaCand":"LR",
        "LibNuaCand":"Les Républicains",
        "Couleur":"#005ce6",
        "Sortant":null,
        "Details":null
    },
    {
        "NumTour":"1",
        "CodDpt":"54",
        "LibDpt":"Meurthe-et-Moselle",
        "CodCirElec":"5406",
        "LibCirElec":"6ème circonscription",
        "NumPanneauCand":"5",
        "PrenomPsn":"Anthony",
        "NomPsn":"BOULOGNE",
        "CodNuaCand":"RN",
        "LibNuaCand":"Rassemblement National",
        "Couleur":"#002E61",
        "Sortant":null,
        "Details":null
    },
    {
        "NumTour":"1",
        "CodDpt":"54",
        "LibDpt":"Meurthe-et-Moselle",
        "CodCirElec":"5406",
        "LibCirElec":"6ème circonscription",
        "NumPanneauCand":"6",
        "PrenomPsn":"Sonia",
        "NomPsn":"THIRION",
        "CodNuaCand":"DSV",
        "LibNuaCand":"Droite souverainiste",
        "Couleur":"#1019c1",
        "Sortant":null,
        "Details":null
    },
    {
        "NumTour":"1",
        "CodDpt":"54",
        "LibDpt":"Meurthe-et-Moselle",
        "CodCirElec":"5406",
        "LibCirElec":"6ème circonscription",
        "NumPanneauCand":"7",
        "PrenomPsn":"Caroline",
        "NomPsn":"FIAT",
        "CodNuaCand":"UG",
        "LibNuaCand":"Union de la gauche",
        "Couleur":"#de3c80",
        "Sortant":null,
        "Details":null
    }
]